[{"Date":"04/13/2022","Open":2.18,"High":2.25,"Low":2.12,"Close":2.22,"Volume":144863.0},{"Date":"04/12/2022","Open":2.15,"High":2.3,"Low":2.15,"Close":2.2,"Volume":65186.0},{"Date":"04/11/2022","Open":2.21,"High":2.23,"Low":2.14,"Close":2.17,"Volume":67735.0},{"Date":"04/08/2022","Open":2.16,"High":2.29,"Low":2.16,"Close":2.21,"Volume":67164.0},{"Date":"04/07/2022","Open":2.327,"High":2.39,"Low":2.15,"Close":2.21,"Volume":118348.0},{"Date":"04/06/2022","Open":2.35,"High":2.37,"Low":2.23,"Close":2.29,"Volume":83485.0},{"Date":"04/05/2022","Open":2.37,"High":2.46,"Low":2.31,"Close":2.33,"Volume":49216.0},{"Date":"04/04/2022","Open":2.38,"High":2.4597,"Low":2.35,"Close":2.38,"Volume":38046.0},{"Date":"04/01/2022","Open":2.46,"High":2.8,"Low":2.36,"Close":2.37,"Volume":79808.0},{"Date":"03/31/2022","Open":2.53,"High":2.6299,"Low":2.4,"Close":2.45,"Volume":83008.0},{"Date":"03/30/2022","Open":2.77,"High":2.77,"Low":2.55,"Close":2.58,"Volume":82280.0},{"Date":"03/29/2022","Open":2.75,"High":2.83,"Low":2.69,"Close":2.72,"Volume":57891.0},{"Date":"03/28/2022","Open":2.76,"High":2.9,"Low":2.62,"Close":2.71,"Volume":114903.0},{"Date":"03/25/2022","Open":3.03,"High":3.03,"Low":2.75,"Close":2.84,"Volume":180031.0},{"Date":"03/24/2022","Open":3.03,"High":3.08,"Low":3.02,"Close":3.04,"Volume":34442.0},{"Date":"03/23/2022","Open":3.44,"High":3.44,"Low":3.005,"Close":3.04,"Volume":99844.0},{"Date":"03/22/2022","Open":3.26,"High":3.47,"Low":3.16,"Close":3.45,"Volume":81639.0},{"Date":"03/21/2022","Open":3.14,"High":3.25,"Low":2.98,"Close":3.25,"Volume":68669.0},{"Date":"03/18/2022","Open":3.13,"High":3.312,"Low":2.87,"Close":3.14,"Volume":184993.0},{"Date":"03/17/2022","Open":2.89,"High":3.15,"Low":2.89,"Close":3.13,"Volume":60186.0},{"Date":"03/16/2022","Open":2.88,"High":2.9,"Low":2.69,"Close":2.9,"Volume":67631.0},{"Date":"03/15/2022","Open":2.83,"High":2.83,"Low":2.69,"Close":2.77,"Volume":45324.0},{"Date":"03/14/2022","Open":2.81,"High":2.81,"Low":2.58,"Close":2.78,"Volume":52720.0},{"Date":"03/11/2022","Open":2.96,"High":2.96,"Low":2.68,"Close":2.79,"Volume":60666.0},{"Date":"03/10/2022","Open":3.08,"High":3.08,"Low":2.84,"Close":2.96,"Volume":122013.0},{"Date":"03/09/2022","Open":2.83,"High":3.1,"Low":2.82,"Close":3.1,"Volume":72393.0},{"Date":"03/08/2022","Open":2.84,"High":2.89,"Low":2.73,"Close":2.78,"Volume":41389.0},{"Date":"03/07/2022","Open":2.78,"High":2.87,"Low":2.73,"Close":2.84,"Volume":71701.0},{"Date":"03/04/2022","Open":2.87,"High":3.04,"Low":2.72,"Close":2.76,"Volume":55853.0},{"Date":"03/03/2022","Open":3.08,"High":3.08,"Low":2.8333,"Close":2.87,"Volume":65149.0},{"Date":"03/02/2022","Open":3.22,"High":3.42,"Low":2.93,"Close":3.04,"Volume":193884.0},{"Date":"03/01/2022","Open":2.88,"High":3.22,"Low":2.74,"Close":3.2,"Volume":242318.0},{"Date":"02/28/2022","Open":2.5,"High":2.7901,"Low":2.45,"Close":2.74,"Volume":200338.0},{"Date":"02/25/2022","Open":2.45,"High":2.5,"Low":2.34,"Close":2.48,"Volume":136758.0},{"Date":"02/24/2022","Open":2.04,"High":2.49,"Low":2.03,"Close":2.46,"Volume":388860.0},{"Date":"02/23/2022","Open":2.22,"High":2.22,"Low":2.03,"Close":2.07,"Volume":79571.0},{"Date":"02/22/2022","Open":2.16,"High":2.25,"Low":2.01,"Close":2.18,"Volume":139020.0},{"Date":"02/18/2022","Open":2.01,"High":2.06,"Low":2.01,"Close":2.03,"Volume":89877.0},{"Date":"02/17/2022","Open":2.11,"High":2.12,"Low":2.0,"Close":2.0,"Volume":209101.0},{"Date":"02/16/2022","Open":2.02,"High":2.15,"Low":2.0,"Close":2.13,"Volume":175509.0},{"Date":"02/15/2022","Open":2.03,"High":2.08,"Low":2.0,"Close":2.02,"Volume":75291.0},{"Date":"02/14/2022","Open":2.13,"High":2.21,"Low":2.0,"Close":2.03,"Volume":127314.0},{"Date":"02/11/2022","Open":2.18,"High":2.3,"Low":2.11,"Close":2.12,"Volume":161193.0},{"Date":"02/10/2022","Open":2.17,"High":2.4,"Low":2.17,"Close":2.2,"Volume":138260.0},{"Date":"02/09/2022","Open":2.21,"High":2.25,"Low":2.1574,"Close":2.22,"Volume":324057.0},{"Date":"02/08/2022","Open":2.24,"High":2.31,"Low":2.08,"Close":2.15,"Volume":48248.0},{"Date":"02/07/2022","Open":2.09,"High":2.25,"Low":2.0,"Close":2.18,"Volume":186364.0},{"Date":"02/04/2022","Open":2.1,"High":2.11,"Low":2.0,"Close":2.06,"Volume":116627.0},{"Date":"02/03/2022","Open":2.26,"High":2.28,"Low":2.08,"Close":2.11,"Volume":89950.0},{"Date":"02/02/2022","Open":2.33,"High":2.36,"Low":2.24,"Close":2.32,"Volume":127946.0},{"Date":"02/01/2022","Open":2.16,"High":2.37,"Low":2.16,"Close":2.29,"Volume":104514.0},{"Date":"01/31/2022","Open":2.04,"High":2.235,"Low":2.04,"Close":2.2,"Volume":134944.0},{"Date":"01/28/2022","Open":1.98,"High":2.07,"Low":1.92,"Close":2.07,"Volume":258679.0},{"Date":"01/27/2022","Open":2.03,"High":2.04,"Low":1.95,"Close":2.0,"Volume":164106.0},{"Date":"01/26/2022","Open":2.08,"High":2.16,"Low":2.0,"Close":2.03,"Volume":146096.0},{"Date":"01/25/2022","Open":2.08,"High":2.1125,"Low":1.96,"Close":2.08,"Volume":436622.0},{"Date":"01/24/2022","Open":2.05,"High":2.14,"Low":1.875,"Close":2.09,"Volume":153968.0},{"Date":"01/21/2022","Open":2.19,"High":2.23,"Low":2.06,"Close":2.06,"Volume":159654.0},{"Date":"01/20/2022","Open":2.23,"High":2.4739,"Low":2.22,"Close":2.23,"Volume":174360.0},{"Date":"01/19/2022","Open":2.27,"High":2.3098,"Low":2.16,"Close":2.24,"Volume":78540.0},{"Date":"01/18/2022","Open":2.4,"High":2.41,"Low":2.2,"Close":2.25,"Volume":163384.0},{"Date":"01/14/2022","Open":2.34,"High":2.4109,"Low":2.28,"Close":2.39,"Volume":97529.0},{"Date":"01/13/2022","Open":2.32,"High":2.43,"Low":2.3,"Close":2.36,"Volume":150269.0},{"Date":"01/12/2022","Open":2.59,"High":2.66,"Low":2.4,"Close":2.42,"Volume":160219.0},{"Date":"01/11/2022","Open":2.68,"High":2.7,"Low":2.6,"Close":2.62,"Volume":71303.0},{"Date":"01/10/2022","Open":2.67,"High":2.7,"Low":2.5,"Close":2.66,"Volume":157596.0},{"Date":"01/07/2022","Open":2.66,"High":2.72,"Low":2.62,"Close":2.67,"Volume":176303.0},{"Date":"01/06/2022","Open":2.64,"High":2.69,"Low":2.5501,"Close":2.63,"Volume":88676.0},{"Date":"01/05/2022","Open":2.77,"High":2.95,"Low":2.74,"Close":2.74,"Volume":184853.0},{"Date":"01/04/2022","Open":2.81,"High":2.85,"Low":2.78,"Close":2.8,"Volume":83256.0},{"Date":"01/03/2022","Open":2.5909,"High":2.87,"Low":2.5909,"Close":2.82,"Volume":80668.0},{"Date":"12/31/2021","Open":2.53,"High":2.77,"Low":2.53,"Close":2.69,"Volume":126830.0},{"Date":"12/30/2021","Open":2.62,"High":2.7,"Low":2.53,"Close":2.55,"Volume":286344.0},{"Date":"12/29/2021","Open":2.73,"High":2.73,"Low":2.46,"Close":2.61,"Volume":354146.0},{"Date":"12/28/2021","Open":2.66,"High":2.9,"Low":2.65,"Close":2.75,"Volume":273533.0},{"Date":"12/27/2021","Open":3.07,"High":3.07,"Low":2.685,"Close":2.7,"Volume":294960.0},{"Date":"12/23/2021","Open":2.64,"High":3.14,"Low":2.62,"Close":3.03,"Volume":605442.0},{"Date":"12/22/2021","Open":2.33,"High":2.7,"Low":2.23,"Close":2.64,"Volume":679156.0},{"Date":"12/21/2021","Open":2.59,"High":2.68,"Low":2.4,"Close":2.45,"Volume":592439.0},{"Date":"12/20/2021","Open":2.79,"High":2.9935,"Low":2.42,"Close":2.59,"Volume":1689336.0},{"Date":"12/17/2021","Open":4.7,"High":5.03,"Low":4.54,"Close":4.98,"Volume":386683.0},{"Date":"12/16/2021","Open":4.77,"High":4.85,"Low":4.65,"Close":4.73,"Volume":80050.0},{"Date":"12/15/2021","Open":4.66,"High":4.81,"Low":4.4199,"Close":4.75,"Volume":120666.0},{"Date":"12/14/2021","Open":4.66,"High":4.82,"Low":4.58,"Close":4.63,"Volume":99009.0},{"Date":"12/13/2021","Open":5.05,"High":5.07,"Low":4.59,"Close":4.72,"Volume":114001.0},{"Date":"12/10/2021","Open":4.95,"High":5.2196,"Low":4.815,"Close":4.96,"Volume":233217.0},{"Date":"12/09/2021","Open":5.07,"High":5.13,"Low":4.87,"Close":4.9,"Volume":92846.0},{"Date":"12/08/2021","Open":5.26,"High":5.26,"Low":5.11,"Close":5.12,"Volume":73203.0},{"Date":"12/07/2021","Open":5.09,"High":5.3,"Low":5.0483,"Close":5.24,"Volume":119393.0},{"Date":"12/06/2021","Open":5.04,"High":5.16,"Low":4.93,"Close":5.03,"Volume":161295.0},{"Date":"12/03/2021","Open":5.18,"High":5.18,"Low":4.93,"Close":5.0,"Volume":307986.0},{"Date":"12/02/2021","Open":4.89,"High":5.18,"Low":4.8725,"Close":5.14,"Volume":145711.0},{"Date":"12/01/2021","Open":5.19,"High":5.19,"Low":4.9,"Close":4.9,"Volume":80227.0},{"Date":"11/30/2021","Open":5.02,"High":5.12,"Low":4.9,"Close":5.08,"Volume":123138.0},{"Date":"11/29/2021","Open":5.28,"High":5.29,"Low":5.02,"Close":5.05,"Volume":83769.0},{"Date":"11/26/2021","Open":5.36,"High":5.4309,"Low":5.13,"Close":5.16,"Volume":55167.0},{"Date":"11/24/2021","Open":5.25,"High":5.43,"Low":5.2,"Close":5.43,"Volume":62392.0},{"Date":"11/23/2021","Open":5.23,"High":5.28,"Low":5.05,"Close":5.26,"Volume":97874.0},{"Date":"11/22/2021","Open":5.42,"High":5.45,"Low":5.16,"Close":5.18,"Volume":125795.0},{"Date":"11/19/2021","Open":5.55,"High":5.65,"Low":5.3,"Close":5.35,"Volume":140439.0},{"Date":"11/18/2021","Open":5.54,"High":5.649,"Low":5.37,"Close":5.5,"Volume":177278.0},{"Date":"11/17/2021","Open":5.08,"High":5.79,"Low":5.0164,"Close":5.41,"Volume":316283.0},{"Date":"11/16/2021","Open":5.2,"High":5.26,"Low":5.0,"Close":5.11,"Volume":153151.0},{"Date":"11/15/2021","Open":5.26,"High":5.41,"Low":5.15,"Close":5.2,"Volume":84598.0},{"Date":"11/12/2021","Open":5.26,"High":5.46,"Low":5.08,"Close":5.4,"Volume":76427.0},{"Date":"11/11/2021","Open":5.29,"High":5.39,"Low":5.06,"Close":5.28,"Volume":118814.0},{"Date":"11/10/2021","Open":5.39,"High":5.42,"Low":5.25,"Close":5.28,"Volume":50140.0},{"Date":"11/09/2021","Open":5.52,"High":5.52,"Low":5.32,"Close":5.39,"Volume":52305.0},{"Date":"11/08/2021","Open":5.64,"High":5.68,"Low":5.44,"Close":5.54,"Volume":66342.0},{"Date":"11/05/2021","Open":5.49,"High":5.66,"Low":5.44,"Close":5.64,"Volume":77393.0},{"Date":"11/04/2021","Open":5.52,"High":5.56,"Low":5.37,"Close":5.46,"Volume":76357.0},{"Date":"11/03/2021","Open":5.31,"High":5.7024,"Low":5.31,"Close":5.54,"Volume":270351.0},{"Date":"11/02/2021","Open":5.23,"High":5.36,"Low":5.22,"Close":5.35,"Volume":28502.0},{"Date":"11/01/2021","Open":5.17,"High":5.35,"Low":5.1401,"Close":5.23,"Volume":94711.0},{"Date":"10/29/2021","Open":5.21,"High":5.23,"Low":5.05,"Close":5.16,"Volume":82044.0},{"Date":"10/28/2021","Open":5.16,"High":5.29,"Low":5.0604,"Close":5.25,"Volume":55112.0},{"Date":"10/27/2021","Open":5.21,"High":5.23,"Low":5.1386,"Close":5.15,"Volume":44414.0},{"Date":"10/26/2021","Open":5.05,"High":5.23,"Low":4.96,"Close":5.19,"Volume":67275.0},{"Date":"10/25/2021","Open":4.99,"High":5.09,"Low":4.99,"Close":5.08,"Volume":159064.0},{"Date":"10/22/2021","Open":5.09,"High":5.1298,"Low":4.9,"Close":4.98,"Volume":121244.0},{"Date":"10/21/2021","Open":5.18,"High":5.3545,"Low":5.04,"Close":5.06,"Volume":59334.0},{"Date":"10/20/2021","Open":5.19,"High":5.2699,"Low":5.1197,"Close":5.2,"Volume":37209.0},{"Date":"10/19/2021","Open":5.11,"High":5.18,"Low":5.01,"Close":5.16,"Volume":113768.0},{"Date":"10/18/2021","Open":5.12,"High":5.169,"Low":4.89,"Close":5.06,"Volume":135052.0},{"Date":"10/15/2021","Open":5.37,"High":5.37,"Low":5.1001,"Close":5.15,"Volume":76482.0},{"Date":"10/14/2021","Open":5.38,"High":5.56,"Low":5.26,"Close":5.28,"Volume":68267.0},{"Date":"10/13/2021","Open":5.22,"High":5.48,"Low":5.22,"Close":5.36,"Volume":102893.0},{"Date":"10/12/2021","Open":5.2,"High":5.32,"Low":5.2,"Close":5.27,"Volume":59059.0},{"Date":"10/11/2021","Open":5.0,"High":5.26,"Low":4.9771,"Close":5.18,"Volume":84361.0},{"Date":"10/08/2021","Open":5.09,"High":5.09,"Low":4.9,"Close":4.98,"Volume":79919.0},{"Date":"10/07/2021","Open":4.9,"High":5.18,"Low":4.87,"Close":5.03,"Volume":120124.0},{"Date":"10/06/2021","Open":4.99,"High":4.99,"Low":4.7587,"Close":4.9,"Volume":109377.0},{"Date":"10/05/2021","Open":5.11,"High":5.12,"Low":4.75,"Close":5.01,"Volume":159730.0},{"Date":"10/04/2021","Open":5.16,"High":5.21,"Low":5.01,"Close":5.12,"Volume":124678.0},{"Date":"10/01/2021","Open":4.96,"High":5.15,"Low":4.96,"Close":5.11,"Volume":152092.0},{"Date":"09/30/2021","Open":4.9,"High":5.13,"Low":4.76,"Close":5.01,"Volume":152920.0},{"Date":"09/29/2021","Open":5.08,"High":5.1217,"Low":4.77,"Close":4.83,"Volume":167487.0},{"Date":"09/28/2021","Open":5.2,"High":5.2,"Low":4.94,"Close":4.99,"Volume":135935.0},{"Date":"09/27/2021","Open":5.22,"High":5.3,"Low":5.01,"Close":5.21,"Volume":198462.0},{"Date":"09/24/2021","Open":5.38,"High":5.47,"Low":5.08,"Close":5.22,"Volume":176151.0},{"Date":"09/23/2021","Open":5.25,"High":6.26,"Low":5.212,"Close":5.38,"Volume":981844.0},{"Date":"09/22/2021","Open":5.15,"High":5.484,"Low":4.7096,"Close":5.18,"Volume":895964.0},{"Date":"09/21/2021","Open":6.44,"High":6.54,"Low":6.33,"Close":6.48,"Volume":155005.0},{"Date":"09/20/2021","Open":6.26,"High":6.785,"Low":6.26,"Close":6.38,"Volume":210752.0},{"Date":"09/17/2021","Open":6.54,"High":6.74,"Low":6.29,"Close":6.38,"Volume":473445.0},{"Date":"09/16/2021","Open":6.46,"High":6.5,"Low":6.3,"Close":6.49,"Volume":60154.0},{"Date":"09/15/2021","Open":6.35,"High":6.58,"Low":6.31,"Close":6.44,"Volume":81411.0},{"Date":"09/14/2021","Open":6.29,"High":6.52,"Low":6.29,"Close":6.4,"Volume":80186.0},{"Date":"09/13/2021","Open":6.51,"High":6.61,"Low":6.21,"Close":6.31,"Volume":103587.0},{"Date":"09/10/2021","Open":6.65,"High":6.7,"Low":6.45,"Close":6.5,"Volume":100523.0},{"Date":"09/09/2021","Open":6.49,"High":6.87,"Low":6.42,"Close":6.59,"Volume":128535.0},{"Date":"09/08/2021","Open":6.85,"High":6.8842,"Low":6.44,"Close":6.47,"Volume":197692.0},{"Date":"09/07/2021","Open":7.36,"High":7.5,"Low":6.72,"Close":6.76,"Volume":223596.0},{"Date":"09/03/2021","Open":7.45,"High":7.55,"Low":7.235,"Close":7.36,"Volume":124964.0},{"Date":"09/02/2021","Open":7.23,"High":7.72,"Low":7.23,"Close":7.48,"Volume":185520.0},{"Date":"09/01/2021","Open":8.02,"High":8.05,"Low":6.99,"Close":7.28,"Volume":537027.0},{"Date":"08/31/2021","Open":8.06,"High":8.17,"Low":7.81,"Close":7.97,"Volume":86122.0},{"Date":"08/30/2021","Open":8.23,"High":8.385,"Low":7.92,"Close":8.03,"Volume":108443.0},{"Date":"08/27/2021","Open":8.19,"High":8.3,"Low":7.92,"Close":8.27,"Volume":132688.0},{"Date":"08/26/2021","Open":7.95,"High":8.3,"Low":7.93,"Close":8.09,"Volume":231729.0},{"Date":"08/25/2021","Open":8.1,"High":8.175,"Low":7.9,"Close":7.97,"Volume":175662.0},{"Date":"08/24/2021","Open":8.02,"High":8.14,"Low":7.855,"Close":8.1,"Volume":102588.0},{"Date":"08/23/2021","Open":7.79,"High":8.22,"Low":7.79,"Close":7.97,"Volume":177794.0},{"Date":"08/20/2021","Open":7.1,"High":7.85,"Low":7.1,"Close":7.7,"Volume":155646.0},{"Date":"08/19/2021","Open":7.1,"High":7.32,"Low":7.03,"Close":7.16,"Volume":93882.0},{"Date":"08/18/2021","Open":7.25,"High":7.43,"Low":7.1,"Close":7.14,"Volume":91411.0},{"Date":"08/17/2021","Open":7.46,"High":7.56,"Low":7.1,"Close":7.23,"Volume":111321.0},{"Date":"08/16/2021","Open":7.93,"High":7.93,"Low":7.33,"Close":7.46,"Volume":117854.0},{"Date":"08/13/2021","Open":7.9,"High":8.08,"Low":7.8,"Close":7.92,"Volume":69271.0},{"Date":"08/12/2021","Open":7.8,"High":7.94,"Low":7.51,"Close":7.92,"Volume":89245.0},{"Date":"08/11/2021","Open":8.15,"High":8.2697,"Low":7.45,"Close":7.78,"Volume":167304.0},{"Date":"08/10/2021","Open":8.06,"High":8.2,"Low":7.91,"Close":8.1,"Volume":106879.0},{"Date":"08/09/2021","Open":7.93,"High":8.12,"Low":7.89,"Close":8.06,"Volume":75300.0},{"Date":"08/06/2021","Open":8.0,"High":8.0,"Low":7.73,"Close":7.91,"Volume":126138.0},{"Date":"08/05/2021","Open":7.89,"High":8.03,"Low":7.809,"Close":8.0,"Volume":144236.0},{"Date":"08/04/2021","Open":7.92,"High":8.2933,"Low":7.78,"Close":7.92,"Volume":178993.0},{"Date":"08/03/2021","Open":7.74,"High":8.09,"Low":7.4527,"Close":7.97,"Volume":67840.0},{"Date":"08/02/2021","Open":7.38,"High":7.88,"Low":7.2776,"Close":7.75,"Volume":114023.0},{"Date":"07/30/2021","Open":7.419,"High":7.68,"Low":7.08,"Close":7.33,"Volume":90739.0},{"Date":"07/29/2021","Open":8.05,"High":8.15,"Low":7.6,"Close":7.69,"Volume":78706.0},{"Date":"07/28/2021","Open":7.62,"High":8.15,"Low":7.4367,"Close":7.99,"Volume":123953.0},{"Date":"07/27/2021","Open":7.63,"High":7.69,"Low":7.37,"Close":7.57,"Volume":76621.0},{"Date":"07/26/2021","Open":8.03,"High":8.13,"Low":7.44,"Close":7.63,"Volume":141221.0},{"Date":"07/23/2021","Open":7.99,"High":8.17,"Low":7.67,"Close":8.0,"Volume":555138.0},{"Date":"07/22/2021","Open":7.62,"High":8.0,"Low":7.57,"Close":7.93,"Volume":234776.0},{"Date":"07/21/2021","Open":7.55,"High":7.65,"Low":7.44,"Close":7.65,"Volume":80999.0},{"Date":"07/20/2021","Open":6.94,"High":7.53,"Low":6.88,"Close":7.53,"Volume":152829.0},{"Date":"07/19/2021","Open":6.99,"High":7.125,"Low":6.83,"Close":6.89,"Volume":95303.0},{"Date":"07/16/2021","Open":7.08,"High":7.28,"Low":6.89,"Close":7.08,"Volume":98305.0},{"Date":"07/15/2021","Open":7.14,"High":7.19,"Low":6.79,"Close":7.03,"Volume":146012.0},{"Date":"07/14/2021","Open":7.33,"High":7.33,"Low":7.1,"Close":7.13,"Volume":81956.0},{"Date":"07/13/2021","Open":7.39,"High":7.5,"Low":7.18,"Close":7.29,"Volume":119412.0},{"Date":"07/12/2021","Open":7.6,"High":7.7012,"Low":7.18,"Close":7.43,"Volume":147182.0},{"Date":"07/09/2021","Open":7.3,"High":7.6,"Low":7.255,"Close":7.52,"Volume":75477.0},{"Date":"07/08/2021","Open":7.18,"High":7.26,"Low":7.0,"Close":7.2,"Volume":89872.0},{"Date":"07/07/2021","Open":7.56,"High":7.58,"Low":7.2,"Close":7.41,"Volume":79281.0},{"Date":"07/06/2021","Open":7.78,"High":7.91,"Low":7.56,"Close":7.63,"Volume":130891.0},{"Date":"07/02/2021","Open":8.07,"High":8.07,"Low":7.575,"Close":7.75,"Volume":247440.0},{"Date":"07/01/2021","Open":7.38,"High":8.07,"Low":7.38,"Close":8.01,"Volume":172578.0},{"Date":"06/30/2021","Open":7.46,"High":7.56,"Low":7.2976,"Close":7.46,"Volume":128047.0},{"Date":"06/29/2021","Open":7.11,"High":7.51,"Low":6.95,"Close":7.43,"Volume":165424.0},{"Date":"06/28/2021","Open":6.75,"High":7.38,"Low":6.67,"Close":7.15,"Volume":256994.0},{"Date":"06/25/2021","Open":6.48,"High":6.8,"Low":6.45,"Close":6.68,"Volume":2573715.0},{"Date":"06/24/2021","Open":6.69,"High":6.71,"Low":6.4,"Close":6.44,"Volume":260730.0},{"Date":"06/23/2021","Open":6.57,"High":6.68,"Low":6.41,"Close":6.47,"Volume":151368.0},{"Date":"06/22/2021","Open":6.44,"High":6.66,"Low":6.33,"Close":6.56,"Volume":134941.0},{"Date":"06/21/2021","Open":6.68,"High":6.713,"Low":6.33,"Close":6.53,"Volume":177978.0},{"Date":"06/18/2021","Open":6.64,"High":6.71,"Low":6.3,"Close":6.61,"Volume":1277885.0},{"Date":"06/17/2021","Open":6.6,"High":6.7,"Low":6.25,"Close":6.67,"Volume":247457.0},{"Date":"06/16/2021","Open":6.56,"High":6.77,"Low":6.4,"Close":6.61,"Volume":183939.0},{"Date":"06/15/2021","Open":6.75,"High":6.75,"Low":6.35,"Close":6.56,"Volume":186716.0},{"Date":"06/14/2021","Open":6.83,"High":6.96,"Low":6.51,"Close":6.62,"Volume":208907.0},{"Date":"06/11/2021","Open":7.09,"High":7.28,"Low":6.81,"Close":6.82,"Volume":184403.0},{"Date":"06/10/2021","Open":7.42,"High":7.44,"Low":7.05,"Close":7.11,"Volume":157381.0},{"Date":"06/09/2021","Open":7.68,"High":7.73,"Low":7.25,"Close":7.38,"Volume":161244.0},{"Date":"06/08/2021","Open":8.07,"High":8.5,"Low":7.17,"Close":7.66,"Volume":645404.0},{"Date":"06/07/2021","Open":8.02,"High":8.12,"Low":7.805,"Close":7.95,"Volume":335481.0},{"Date":"06/04/2021","Open":7.9,"High":8.07,"Low":7.67,"Close":8.0,"Volume":223875.0},{"Date":"06/03/2021","Open":7.79,"High":7.8799,"Low":7.65,"Close":7.77,"Volume":141660.0},{"Date":"06/02/2021","Open":7.93,"High":8.16,"Low":7.64,"Close":8.01,"Volume":183641.0},{"Date":"06/01/2021","Open":7.81,"High":7.98,"Low":7.42,"Close":7.95,"Volume":205964.0},{"Date":"05/28/2021","Open":7.95,"High":8.07,"Low":7.75,"Close":7.82,"Volume":126231.0},{"Date":"05/27/2021","Open":8.19,"High":8.31,"Low":7.71,"Close":7.91,"Volume":156883.0},{"Date":"05/26/2021","Open":8.0,"High":8.3599,"Low":7.75,"Close":8.17,"Volume":217312.0},{"Date":"05/25/2021","Open":7.62,"High":7.95,"Low":7.3,"Close":7.94,"Volume":369011.0},{"Date":"05/24/2021","Open":8.42,"High":8.49,"Low":7.61,"Close":7.65,"Volume":274324.0},{"Date":"05/21/2021","Open":7.65,"High":8.7,"Low":7.5401,"Close":8.46,"Volume":442253.0},{"Date":"05/20/2021","Open":7.2,"High":7.71,"Low":6.9701,"Close":7.53,"Volume":276030.0},{"Date":"05/19/2021","Open":7.607,"High":7.85,"Low":6.9,"Close":7.1,"Volume":501014.0},{"Date":"05/18/2021","Open":6.78,"High":8.09,"Low":6.7601,"Close":8.04,"Volume":1097656.0},{"Date":"05/17/2021","Open":6.034,"High":7.43,"Low":5.74,"Close":6.85,"Volume":2411287.0},{"Date":"05/14/2021","Open":5.56,"High":5.6,"Low":5.35,"Close":5.41,"Volume":225862.0},{"Date":"05/13/2021","Open":5.48,"High":5.5,"Low":5.26,"Close":5.43,"Volume":64003.0},{"Date":"05/12/2021","Open":5.65,"High":5.745,"Low":5.33,"Close":5.47,"Volume":83657.0},{"Date":"05/11/2021","Open":5.6,"High":5.91,"Low":5.48,"Close":5.6,"Volume":139317.0},{"Date":"05/10/2021","Open":5.83,"High":5.98,"Low":5.5,"Close":5.61,"Volume":127698.0},{"Date":"05/07/2021","Open":6.01,"High":6.15,"Low":5.77,"Close":5.82,"Volume":126840.0},{"Date":"05/06/2021","Open":6.15,"High":6.22,"Low":5.84,"Close":5.95,"Volume":48595.0},{"Date":"05/05/2021","Open":6.12,"High":6.29,"Low":5.915,"Close":6.12,"Volume":80102.0},{"Date":"05/04/2021","Open":6.4,"High":6.43,"Low":6.055,"Close":6.07,"Volume":97036.0},{"Date":"05/03/2021","Open":6.36,"High":6.71,"Low":6.1701,"Close":6.43,"Volume":81948.0},{"Date":"04/30/2021","Open":6.19,"High":6.57,"Low":6.1613,"Close":6.37,"Volume":68924.0},{"Date":"04/29/2021","Open":6.37,"High":6.49,"Low":6.1211,"Close":6.25,"Volume":87166.0},{"Date":"04/28/2021","Open":5.92,"High":6.66,"Low":5.9075,"Close":6.34,"Volume":132734.0},{"Date":"04/27/2021","Open":6.03,"High":6.2,"Low":5.72,"Close":5.98,"Volume":122180.0},{"Date":"04/26/2021","Open":5.69,"High":6.1,"Low":5.6643,"Close":6.03,"Volume":137617.0},{"Date":"04/23/2021","Open":5.73,"High":5.83,"Low":5.565,"Close":5.6,"Volume":71235.0},{"Date":"04/22/2021","Open":5.43,"High":5.84,"Low":5.33,"Close":5.73,"Volume":127092.0},{"Date":"04/21/2021","Open":5.11,"High":5.45,"Low":5.11,"Close":5.45,"Volume":103226.0},{"Date":"04/20/2021","Open":5.13,"High":5.15,"Low":5.0401,"Close":5.15,"Volume":97512.0},{"Date":"04/19/2021","Open":5.31,"High":5.33,"Low":5.1148,"Close":5.15,"Volume":86166.0},{"Date":"04/16/2021","Open":5.59,"High":5.59,"Low":5.36,"Close":5.36,"Volume":140515.0},{"Date":"04/15/2021","Open":5.56,"High":5.73,"Low":5.5081,"Close":5.6,"Volume":52905.0},{"Date":"04/14/2021","Open":5.4,"High":5.5799,"Low":5.35,"Close":5.56,"Volume":121202.0}]