{"update_time":"2024-08-17 04:29:52.143848","data":{"SEE":{"FCST":32.07,"FCST_Upper30":34.072,"FCST_Lower30":30.072},"KSS":{"FCST":18.636,"FCST_Upper30":20.052,"FCST_Lower30":17.358},"NKE":{"FCST":63.179,"FCST_Upper30":67.046,"FCST_Lower30":59.233},"MPW":{"FCST":5.028,"FCST_Upper30":5.639,"FCST_Lower30":4.47},"CVS":{"FCST":58.386,"FCST_Upper30":62.407,"FCST_Lower30":54.735},"AAP":{"FCST":55.348,"FCST_Upper30":59.638,"FCST_Lower30":51.673},"DIS":{"FCST":83.186,"FCST_Upper30":87.601,"FCST_Lower30":78.852},"EPAM":{"FCST":221.459,"FCST_Upper30":242.962,"FCST_Lower30":203.444},"CMA":{"FCST":56.658,"FCST_Upper30":60.516,"FCST_Lower30":53.183},"DAC":{"FCST":76.223,"FCST_Upper30":79.945,"FCST_Lower30":72.827},"VALE":{"FCST":9.408,"FCST_Upper30":9.917,"FCST_Lower30":8.908},"SID":{"FCST":1.888,"FCST_Upper30":2.016,"FCST_Lower30":1.77},"ALB":{"FCST":64.05,"FCST_Upper30":70.615,"FCST_Lower30":58.871},"ABNB":{"FCST":119.833,"FCST_Upper30":128.621,"FCST_Lower30":111.493},"ADBE":{"FCST":583.072,"FCST_Upper30":616.498,"FCST_Lower30":551.417},"AEP":{"FCST":102.175,"FCST_Upper30":109.169,"FCST_Lower30":96.114},"APD":{"FCST":266.931,"FCST_Upper30":284.984,"FCST_Lower30":251.209},"APTV":{"FCST":59.788,"FCST_Upper30":64.444,"FCST_Lower30":55.741},"AZO":{"FCST":3296.685,"FCST_Upper30":3580.051,"FCST_Lower30":2989.537},"BBY":{"FCST":83.813,"FCST_Upper30":90.626,"FCST_Lower30":77.722},"BIO":{"FCST":340.558,"FCST_Upper30":362.667,"FCST_Lower30":319.471},"C":{"FCST":61.208,"FCST_Upper30":63.835,"FCST_Lower30":58.641},"CRM":{"FCST":257.859,"FCST_Upper30":275.648,"FCST_Lower30":237.482},"DE":{"FCST":362.45,"FCST_Upper30":381.425,"FCST_Lower30":343.871},"DEO":{"FCST":118.443,"FCST_Upper30":124.315,"FCST_Lower30":112.488},"DELL":{"FCST":87.447,"FCST_Upper30":96.066,"FCST_Lower30":80.388},"DOX":{"FCST":88.97,"FCST_Upper30":91.83,"FCST_Lower30":85.614},"EXLS":{"FCST":37.375,"FCST_Upper30":39.068,"FCST_Lower30":35.829},"F":{"FCST":10.457,"FCST_Upper30":11.359,"FCST_Lower30":9.7},"FDX":{"FCST":331.367,"FCST_Upper30":350.86,"FCST_Lower30":310.98},"FSLR":{"FCST":180.218,"FCST_Upper30":196.672,"FCST_Lower30":164.238},"G":{"FCST":35.296,"FCST_Upper30":36.855,"FCST_Lower30":33.843},"GM":{"FCST":42.949,"FCST_Upper30":45.389,"FCST_Lower30":40.556},"GPC":{"FCST":135.188,"FCST_Upper30":141.573,"FCST_Lower30":129.181},"HI":{"FCST":34.861,"FCST_Upper30":37.079,"FCST_Lower30":32.833},"HPQ":{"FCST":33.967,"FCST_Upper30":36.37,"FCST_Lower30":31.906},"INTC":{"FCST":22.621,"FCST_Upper30":25.451,"FCST_Lower30":20.148},"JKHY":{"FCST":167.515,"FCST_Upper30":173.516,"FCST_Lower30":161.985},"K":{"FCST":69.443,"FCST_Upper30":73.924,"FCST_Lower30":65.208},"LMAT":{"FCST":86.725,"FCST_Upper30":92.824,"FCST_Lower30":81.023},"LQDT":{"FCST":23.256,"FCST_Upper30":24.452,"FCST_Lower30":22.089},"LTHM":{"FCST":15.331,"FCST_Upper30":16.884,"FCST_Lower30":13.98},"M":{"FCST":16.309,"FCST_Upper30":17.728,"FCST_Lower30":15.069},"MCHP":{"FCST":72.736,"FCST_Upper30":76.586,"FCST_Lower30":68.819},"MS":{"FCST":100.855,"FCST_Upper30":106.68,"FCST_Lower30":95.315},"MSFT":{"FCST":405.835,"FCST_Upper30":428.408,"FCST_Lower30":386.528},"MWA":{"FCST":20.756,"FCST_Upper30":21.953,"FCST_Lower30":19.736},"NFLX":{"FCST":609.84,"FCST_Upper30":671.112,"FCST_Lower30":563.24},"NOW":{"FCST":858.26,"FCST_Upper30":933.391,"FCST_Lower30":787.155},"ORCL":{"FCST":139.976,"FCST_Upper30":149.214,"FCST_Lower30":131.126},"OSIS":{"FCST":138.898,"FCST_Upper30":145.535,"FCST_Lower30":132.457},"PAYC":{"FCST":157.742,"FCST_Upper30":177.498,"FCST_Lower30":138.459},"PCTY":{"FCST":150.564,"FCST_Upper30":165.997,"FCST_Lower30":138.008},"PEP":{"FCST":173.444,"FCST_Upper30":183.132,"FCST_Lower30":164.347},"PHG":{"FCST":27.454,"FCST_Upper30":29.484,"FCST_Lower30":25.732},"QCOM":{"FCST":146.796,"FCST_Upper30":156.813,"FCST_Lower30":137.395},"SIMO":{"FCST":57.554,"FCST_Upper30":61.225,"FCST_Lower30":54.201},"SMP":{"FCST":30.285,"FCST_Upper30":32.363,"FCST_Lower30":28.248},"SQM":{"FCST":31.13,"FCST_Upper30":33.898,"FCST_Lower30":28.947},"TECH":{"FCST":72.075,"FCST_Upper30":78.179,"FCST_Lower30":65.717},"TITN":{"FCST":13.91,"FCST_Upper30":14.828,"FCST_Lower30":12.971},"TNP":{"FCST":21.67,"FCST_Upper30":23.471,"FCST_Lower30":20.01},"TX":{"FCST":29.865,"FCST_Upper30":31.492,"FCST_Lower30":28.424},"VEEV":{"FCST":188.726,"FCST_Upper30":203.619,"FCST_Lower30":173.392},"WDAY":{"FCST":222.692,"FCST_Upper30":241.699,"FCST_Lower30":205.16},"WNS":{"FCST":61.302,"FCST_Upper30":66.178,"FCST_Lower30":57.222},"X":{"FCST":42.751,"FCST_Upper30":45.298,"FCST_Lower30":40.04},"GIS":{"FCST":68.109,"FCST_Upper30":70.714,"FCST_Lower30":65.631},"SBUX":{"FCST":77.898,"FCST_Upper30":82.756,"FCST_Lower30":73.465},"EL":{"FCST":80.295,"FCST_Upper30":86.493,"FCST_Lower30":73.994},"TGT":{"FCST":137.574,"FCST_Upper30":146.598,"FCST_Lower30":128.748},"VFC":{"FCST":19.322,"FCST_Upper30":20.794,"FCST_Lower30":17.941},"ILPT":{"FCST":4.84,"FCST_Upper30":5.458,"FCST_Lower30":4.311},"PYPL":{"FCST":59.985,"FCST_Upper30":63.349,"FCST_Lower30":56.892},"EW":{"FCST":59.096,"FCST_Upper30":63.728,"FCST_Lower30":54.708},"ZIM":{"FCST":16.539,"FCST_Upper30":19.099,"FCST_Lower30":14.345},"HAL":{"FCST":30.933,"FCST_Upper30":32.254,"FCST_Lower30":29.643},"ABM":{"FCST":56.61,"FCST_Upper30":59.664,"FCST_Lower30":53.864},"ACLS":{"FCST":110.772,"FCST_Upper30":121.361,"FCST_Lower30":101.103},"ADSK":{"FCST":256.497,"FCST_Upper30":270.291,"FCST_Lower30":243.423},"ALGM":{"FCST":21.377,"FCST_Upper30":23.193,"FCST_Lower30":19.627},"ALGN":{"FCST":197.284,"FCST_Upper30":214.769,"FCST_Lower30":180.256},"ANSS":{"FCST":300.947,"FCST_Upper30":319.373,"FCST_Lower30":284.104},"ASML":{"FCST":786.805,"FCST_Upper30":858.92,"FCST_Lower30":717.491},"BAC":{"FCST":40.064,"FCST_Upper30":41.762,"FCST_Lower30":38.214},"BF-B":{"FCST":43.853,"FCST_Upper30":46.192,"FCST_Lower30":41.518},"BK":{"FCST":67.916,"FCST_Upper30":70.276,"FCST_Lower30":65.401},"CNMD":{"FCST":63.505,"FCST_Upper30":67.777,"FCST_Lower30":59.194},"CSCO":{"FCST":46.473,"FCST_Upper30":48.128,"FCST_Lower30":45.007},"DG":{"FCST":108.277,"FCST_Upper30":115.181,"FCST_Lower30":102.146},"DHI":{"FCST":191.753,"FCST_Upper30":204.983,"FCST_Lower30":179.453},"EQNR":{"FCST":26.022,"FCST_Upper30":27.062,"FCST_Lower30":25.044},"EXR":{"FCST":174.19,"FCST_Upper30":186.233,"FCST_Lower30":163.375},"FFIV":{"FCST":200.687,"FCST_Upper30":209.956,"FCST_Lower30":190.323},"FTNT":{"FCST":64.119,"FCST_Upper30":68.118,"FCST_Lower30":60.587},"GLOB":{"FCST":205.026,"FCST_Upper30":222.704,"FCST_Lower30":190.094},"GOOG":{"FCST":162.584,"FCST_Upper30":170.07,"FCST_Lower30":155.267},"HAS":{"FCST":62.812,"FCST_Upper30":67.202,"FCST_Lower30":58.683},"HPE":{"FCST":19.024,"FCST_Upper30":20.264,"FCST_Lower30":17.627},"IPG":{"FCST":29.412,"FCST_Upper30":30.48,"FCST_Lower30":28.358},"ISRG":{"FCST":485.34,"FCST_Upper30":518.334,"FCST_Lower30":455.394},"JPM":{"FCST":216.182,"FCST_Upper30":225.878,"FCST_Lower30":206.475},"KMB":{"FCST":142.294,"FCST_Upper30":149.644,"FCST_Lower30":136.359},"LNTH":{"FCST":124.228,"FCST_Upper30":137.614,"FCST_Lower30":111.664},"LVS":{"FCST":35.648,"FCST_Upper30":37.26,"FCST_Lower30":34.051},"MA":{"FCST":453.306,"FCST_Upper30":477.039,"FCST_Lower30":432.219},"MKC":{"FCST":82.177,"FCST_Upper30":88.701,"FCST_Lower30":76.387},"MMM":{"FCST":132.487,"FCST_Upper30":142.481,"FCST_Lower30":123.212},"MU":{"FCST":84.614,"FCST_Upper30":91.355,"FCST_Lower30":77.83},"NDAQ":{"FCST":72.136,"FCST_Upper30":75.811,"FCST_Lower30":68.97},"NICE":{"FCST":166.825,"FCST_Upper30":178.677,"FCST_Lower30":154.215},"NSSC":{"FCST":72.623,"FCST_Upper30":80.213,"FCST_Lower30":65.839},"ORLY":{"FCST":1181.149,"FCST_Upper30":1243.646,"FCST_Lower30":1117.149},"PAGS":{"FCST":13.037,"FCST_Upper30":14.03,"FCST_Lower30":12.172},"PDCO":{"FCST":24.947,"FCST_Upper30":26.372,"FCST_Lower30":23.508},"PFE":{"FCST":29.814,"FCST_Upper30":30.962,"FCST_Lower30":28.71},"PODD":{"FCST":200.023,"FCST_Upper30":215.207,"FCST_Lower30":184.524},"RTX":{"FCST":114.101,"FCST_Upper30":119.552,"FCST_Lower30":108.592},"SONY":{"FCST":91.79,"FCST_Upper30":95.991,"FCST_Lower30":88.055},"TEAM":{"FCST":147.992,"FCST_Upper30":160.525,"FCST_Lower30":135.475},"TEX":{"FCST":54.451,"FCST_Upper30":58.548,"FCST_Lower30":50.805},"TM":{"FCST":167.043,"FCST_Upper30":177.701,"FCST_Lower30":158.7},"TRI":{"FCST":154.47,"FCST_Upper30":164.473,"FCST_Lower30":146.188},"UPS":{"FCST":123.056,"FCST_Upper30":129.057,"FCST_Lower30":116.89},"VMI":{"FCST":295.751,"FCST_Upper30":317.248,"FCST_Lower30":275.958},"WFC":{"FCST":53.641,"FCST_Upper30":56.183,"FCST_Lower30":51.381},"ZTS":{"FCST":186.898,"FCST_Upper30":198.38,"FCST_Lower30":176.128}}}